[
  {
    "code": "473",
    "condition": {
      "procedureBlocks": {
        "neuraxialAnesthesia": {
          "procedureType": "Spinalan채sthesie mit Kathetertechnik | Periduralan채sthesie mit Kathetertechnik | CSE",
          "$maxDuration": 299
        }
      }
    }
  },
  {
    "code": "474",
    "condition": {
      "procedureBlocks": {
        "neuraxialAnesthesia": {
          "procedureType": "Spinalan채sthesie mit Kathetertechnik | Periduralan채sthesie mit Kathetertechnik | CSE",
          "$minDuration": 300
        }
      }
    }
  }
]
